graphyre/__init__.py
graphyre/graphyre.py
graphyre-0.0.1.dist-info/LICENSE
graphyre-0.0.1.dist-info/METADATA
graphyre-0.0.1.dist-info/WHEEL
graphyre-0.0.1.dist-info/entry_points.txt
graphyre-0.0.1.dist-info/top_level.txt
graphyre-0.0.1.dist-info/RECORD
