Metadata-Version: 2.1
Name: graphyre
Version: 0.0.1
Summary: A GraphQL security testing tool
Home-page: https://github.com/SafeEval/graphyre
Author: Jack Sullivan
Author-email: jack@divergent.codes
License: UNKNOWN
Project-URL: Bug Tracker, https://github.com/SafeEval/graphyre/issues
Platform: UNKNOWN
Classifier: Programming Language :: Python :: 3
Classifier: License :: OSI Approved :: MIT License
Classifier: Operating System :: OS Independent
Requires-Python: >=3.8
